dash_auth0_oauth/Auth0_auth.py
dash_auth0_oauth/__init__.py
dash_auth0_oauth/auth.py
dash_auth0_oauth-0.1.5.dist-info/LICENSE
dash_auth0_oauth-0.1.5.dist-info/METADATA
dash_auth0_oauth-0.1.5.dist-info/WHEEL
dash_auth0_oauth-0.1.5.dist-info/top_level.txt
dash_auth0_oauth-0.1.5.dist-info/RECORD
