Metadata-Version: 2.1
Name: dash-auth0-oauth
Version: 0.1.5
Summary: Authenticate to Dash app using Auth0
Home-page: https://github.com/dbrambilla13/dash-auth0-auth
Author: Daniele Brambilla
Author-email: daniele.bram@gmail.com
License: MIT
Platform: UNKNOWN
Requires-Python: >=3.8
License-File: LICENSE
Requires-Dist: dash (>=2.1.0)
Requires-Dist: Flask (>=2.0.2)
Requires-Dist: authlib (>=0.15.5)
Requires-Dist: requests (>=2.27.1)
